tap_prefect/__init__.py
tap_prefect/client.py
tap_prefect/streams.py
tap_prefect/tap.py
tap_prefect/tests/__init__.py
tap_prefect/tests/test_core.py
tap_prefect-0.2.1.dist-info/METADATA
tap_prefect-0.2.1.dist-info/entry_points.txt
tap_prefect-0.2.1.dist-info/WHEEL
tap_prefect-0.2.1.dist-info/RECORD
