Metadata-Version: 2.1
Name: tap-prefect
Version: 0.2.1
Summary: `tap-prefect` is a Singer tap for prefect, built with the Meltano Singer SDK.
License: Apache 2.0
Keywords: ELT,prefect
Author: Datateer Dev
Requires-Python: >=3.7.1,<3.12
Classifier: License :: Other/Proprietary License
Classifier: Programming Language :: Python :: 3
Classifier: Programming Language :: Python :: 3.8
Classifier: Programming Language :: Python :: 3.9
Classifier: Programming Language :: Python :: 3.10
Classifier: Programming Language :: Python :: 3.11
Provides-Extra: s3
Requires-Dist: fs-s3fs (>=1.1.1,<2.0.0) ; extra == "s3"
Requires-Dist: requests (>=2.28.1,<3.0.0)
Requires-Dist: singer-sdk (>=0.18.0,<0.19.0)
